Standard Output:
Standard Error:
Standard Output:
; Main.j

; Generated by ClassFileAnalyzer (Can)
; Analyzer and Disassembler for Java class files
; (Jasmin syntax 2, http://jasmin.sourceforge.net)
;
; ClassFileAnalyzer, version 0.7.0 


.bytecode 65.0
.source Main.java
.class public JasminTestFiles/Main
.super java/lang/Object

.method public <init>()V
  .limit stack 1
  .limit locals 1
  .var 0 is this LJasminTestFiles/Main; from Label0 to Label4
Label0:
  .line 6
  0: aload_0
  1: invokespecial java/lang/Object/<init>()V
Label4:
  4: return
.end method

.method public static f2(ILjava/lang/String;Z)Ljava/lang/String;
  .limit stack 1
  .limit locals 3
  .var 0 is a I from Label0 to Label2
  .var 1 is b Ljava/lang/String; from Label0 to Label2
  .var 2 is c Z from Label0 to Label2
Label0:
  .line 8
  0: ldc "2"
Label2:
  2: areturn
.end method

.method public static f3()Ljava/lang/String;
  .limit stack 1
  .limit locals 0
  .line 12
  0: ldc "3"
  2: areturn
.end method

.method public static f1()Ljava/lang/String;
  .limit stack 1
  .limit locals 0
  .line 17
  0: ldc "1"
  2: areturn
.end method

.method public static f4(I)I
  .limit stack 1
  .limit locals 1
  .var 0 is v I from Label0 to Label1
Label0:
  .line 24
  0: iload_0
Label1:
  1: ireturn
.end method

.method public static f5()I
  .limit stack 1
  .limit locals 0
  .line 28
  0: iconst_2
  1: ireturn
.end method

.method public static f6()Ljava/util/List;
  .limit stack 4
  .limit locals 0
  .line 32
  0: iconst_4
  1: anewarray java/lang/Integer
  4: dup
  5: iconst_0
  6: iconst_1
  7: invokestatic java/lang/Integer/valueOf(I)Ljava/lang/Integer;
  10: aastore
  11: dup
  12: iconst_1
  13: iconst_2
  14: invokestatic java/lang/Integer/valueOf(I)Ljava/lang/Integer;
  17: aastore
  18: dup
  19: iconst_2
  20: iconst_3
  21: invokestatic java/lang/Integer/valueOf(I)Ljava/lang/Integer;
  24: aastore
  25: dup
  26: iconst_3
  27: iconst_4
  28: invokestatic java/lang/Integer/valueOf(I)Ljava/lang/Integer;
  31: aastore
  32: invokestatic java/util/Arrays/asList([Ljava/lang/Object;)Ljava/util/List;
  35: areturn
  .signature "()Ljava/util/List<Ljava/lang/Integer;>;"
.end method

.method public static main([Ljava/lang/String;)V
  .limit stack 1
  .limit locals 1
  .var 0 is args [Ljava/lang/String; from Label0 to Label17
Label0:
  .line 36
  0: invokestatic JasminTestFiles/Main/f1()Ljava/lang/String;
  3: pop
  .line 37
  4: iconst_1
  5: invokestatic JasminTestFiles/Main/f4(I)I
  8: pop
  .line 38
  9: invokestatic JasminTestFiles/Main/f5()I
  12: pop
  .line 39
  13: invokestatic JasminTestFiles/Main/f6()Ljava/util/List;
  16: pop
Label17:
  .line 40
  17: return
.end method


Standard Error:
